viper/__init__.py
viper/api.py
viper/cli.py
viper/console.py
viper/docs.py
viper/readme.rst
viper/typing.py
viper/version
viper/config/__init__.py
viper/config/cli.py
viper/config/config_data.py
viper/config/oshic_sitepdks.py
viper/config/read.py
viper/config/read_config.py
viper/project/Project.py
viper/project/ProjectBuilder.py
viper/project/ProjectConfig.py
viper/project/__init__.py
viper/project/cli.py
viper/project/open.py
viper/results/NgspiceResultReader.py
viper/results/TestDataset.py
viper/schematics/XschemSchematic.py
viper/schematics/__init__.py
viper/simulators/ProjectSimulator.py
viper/simulators/SimResult.py
viper/simulators/TestSimulator.py
viper/simulators/__init__.py
viper/simulators/ngspice.py
viper/testing/PerformanceTest.py
viper/testing/__init__,py
viper_ic-0.1.0.dist-info/entry_points.txt
viper_ic-0.1.0.dist-info/LICENSE
viper_ic-0.1.0.dist-info/WHEEL
viper_ic-0.1.0.dist-info/METADATA
viper_ic-0.1.0.dist-info/RECORD
