Metadata-Version: 2.1
Name: viper-ic
Version: 0.1.0
Summary: Viper open circuit design environment
Author-email: Curtis Mayberry <Curtisma3@gmail.com>
Requires-Python: >=3.8
Classifier: Topic :: Scientific/Engineering :: Electronic Design Automation (EDA)
Classifier: License :: OSI Approved :: MIT License
Classifier: Development Status :: 2 - Pre-Alpha
Classifier: Operating System :: POSIX
Classifier: Environment :: Console
Classifier: Programming Language :: Python :: 3.9
Classifier: Intended Audience :: Science/Research
Classifier: Intended Audience :: End Users/Desktop
Classifier: Typing :: Typed
Classifier: Natural Language :: English
Requires-Dist: click > 8.1, < 9
Requires-Dist: rich >= 12.5, < 13
Requires-Dist: pydantic >= 1.8, < 2
Requires-Dist: toml >= 0.10, < 1
Project-URL: Documentation, http://www.cascode-labs.org/viper/
Project-URL: Source, https://github.com/cascode-labs/viper
